hello/__init__.py
hello/_version.py
hello/hello.py
hello_bro-0.1.5.dist-info/METADATA
hello_bro-0.1.5.dist-info/WHEEL
hello_bro-0.1.5.dist-info/top_level.txt
hello_bro-0.1.5.dist-info/RECORD
