Metadata-Version: 2.4
Name: hello-bro
Version: 0.1.5
Summary: A minimal hello world library
Author: bro
Requires-Python: >=3.8
